bocha_search_mcp/__init__.py
bocha_search_mcp/server.py
bocha_search_mcp-0.0.1.dist-info/METADATA
bocha_search_mcp-0.0.1.dist-info/WHEEL
bocha_search_mcp-0.0.1.dist-info/entry_points.txt
bocha_search_mcp-0.0.1.dist-info/RECORD
