Metadata-Version: 2.4
Name: bocha-search-mcp
Version: 0.0.1
Summary: A
Author-email: kunkun <kunkun@1998.com>
Requires-Python: >=3.12
Requires-Dist: mcp[cli]>=1.6.0
